pyredishelper/__init__.py
pyredishelper/channelconsumer.py
pyredishelper/channelproducer.py
pyredishelper/models.py
pyredishelper/protocols.py
pyredishelper/proxy.py
pyredishelper/queueconsumer.py
pyredishelper/queueproducer.py
pyredishelper/streamconsumer.py
pyredishelper/streamproducer.py
pyredishelper/url_parser.py
pyredishelper-0.0.2.dist-info/LICENSE
pyredishelper-0.0.2.dist-info/METADATA
pyredishelper-0.0.2.dist-info/WHEEL
pyredishelper-0.0.2.dist-info/top_level.txt
pyredishelper-0.0.2.dist-info/RECORD
