Metadata-Version: 2.1
Name: pyredishelper
Version: 0.0.2
Author: mac
Author-email: 
License: MIT License
Classifier: License :: OSI Approved :: MIT License
Classifier: Programming Language :: Python :: 3.7
Classifier: Programming Language :: Python :: 3.8
Classifier: Programming Language :: Python :: 3.9
Classifier: Programming Language :: Python :: 3.10
License-File: LICENSE
Requires-Dist: redis (>=4.4.2)
Requires-Dist: pyproxypattern (>=0.0.1)
